ndp_jupyterlab_git/__init__.py
ndp_jupyterlab_git/_version.py
ndp_jupyterlab_git/git.py
ndp_jupyterlab_git/handlers.py
ndp_jupyterlab_git/log.py
ndp_jupyterlab_git/labextension/build_log.json
ndp_jupyterlab_git/labextension/package.json
ndp_jupyterlab_git/labextension/schemas/@jupyterlab/git/package.json.orig
ndp_jupyterlab_git/labextension/schemas/@jupyterlab/git/plugin.json
ndp_jupyterlab_git/labextension/static/lib_index_js-webpack_sharing_consume_default_codemirror_language-webpack_sharing_consume_defa-fc4736.0a0b01c7dd1f8621ac71.js
ndp_jupyterlab_git/labextension/static/lib_index_js-webpack_sharing_consume_default_codemirror_language-webpack_sharing_consume_defa-fc4736.0a0b01c7dd1f8621ac71.js.map
ndp_jupyterlab_git/labextension/static/lib_index_js-webpack_sharing_consume_default_codemirror_language-webpack_sharing_consume_defa-fc4736.19737f7f1c897a48d896.js
ndp_jupyterlab_git/labextension/static/lib_index_js-webpack_sharing_consume_default_codemirror_language-webpack_sharing_consume_defa-fc4736.19737f7f1c897a48d896.js.map
ndp_jupyterlab_git/labextension/static/lib_index_js-webpack_sharing_consume_default_codemirror_language-webpack_sharing_consume_defa-fc4736.1a909ce0b3268c6b57f4.js
ndp_jupyterlab_git/labextension/static/lib_index_js-webpack_sharing_consume_default_codemirror_language-webpack_sharing_consume_defa-fc4736.1a909ce0b3268c6b57f4.js.map
ndp_jupyterlab_git/labextension/static/lib_index_js-webpack_sharing_consume_default_codemirror_language-webpack_sharing_consume_defa-fc4736.38a9fcb09d7724125fd5.js
ndp_jupyterlab_git/labextension/static/lib_index_js-webpack_sharing_consume_default_codemirror_language-webpack_sharing_consume_defa-fc4736.38a9fcb09d7724125fd5.js.map
ndp_jupyterlab_git/labextension/static/lib_index_js-webpack_sharing_consume_default_codemirror_language-webpack_sharing_consume_defa-fc4736.4b462224af5f18fb71d1.js
ndp_jupyterlab_git-0.50.2.dist-info/METADATA
ndp_jupyterlab_git-0.50.2.dist-info/WHEEL
ndp_jupyterlab_git-0.50.2.dist-info/licenses/LICENSE
ndp_jupyterlab_git-0.50.2.dist-info/RECORD
