Metadata-Version: 2.3
Name: ndp_jupyterlab_git
Version: 0.50.2
Dynamic: Keywords
Summary: A JupyterLab extension for version control using git
Project-URL: Homepage, https://github.com/jupyterlab/jupyterlab-git
Project-URL: Bug Tracker, https://github.com/jupyterlab/jupyterlab-git/issues
Project-URL: Repository, https://github.com/jupyterlab/jupyterlab-git.git
Author: Jupyter Development Team
License: BSD 3-Clause License
License-File: LICENSE
Classifier: Framework :: Jupyter
Classifier: Framework :: Jupyter :: JupyterLab
Classifier: Framework :: Jupyter :: JupyterLab :: 4
Classifier: Framework :: Jupyter :: JupyterLab :: Extensions
Classifier: Framework :: Jupyter :: JupyterLab :: Extensions :: Prebuilt
Classifier: License :: OSI Approved :: BSD License
Classifier: Programming Language :: Python
Classifier: Programming Language :: Python :: 3
Classifier: Programming Language :: Python :: 3.8
Classifier: Programming Language :: Python :: 3.9
Classifier: Programming Language :: Python :: 3.10
Classifier: Programming Language :: Python :: 3.11
Classifier: Programming Language :: Python :: 3.12
Requires-Python: >=3.8
Requires-Dist: jupyter-server<3,>=2.0.1
Requires-Dist: nbdime~=4.0.1
Requires-Dist: nbformat
Requires-Dist: packaging
Requires-Dist: pexpect
Requires-Dist: traitlets~=5.0
Provides-Extra: dev
Requires-Dist: black; extra == 'dev'
Requires-Dist: jupyterlab~=4.0; extra == 'dev'
Requires-Dist: pre-commit; extra == 'dev'
Provides-Extra: test
Requires-Dist: coverage; extra == 'test'
Requires-Dist: jupytext; extra == 'test'
Requires-Dist: pytest; extra == 'test'
Requires-Dist: pytest-asyncio; extra == 'test'
Requires-Dist: pytest-cov; extra == 'test'
Requires-Dist: pytest-jupyter[server]>=0.6.0; extra == 'test'
Provides-Extra: ui-tests
Requires-Dist: jupyter-archive; extra == 'ui-tests'
